{"primaryContentSections":[{"kind":"declarations","declarations":[{"tokens":[{"kind":"keyword","text":"init"},{"kind":"text","text":"("},{"kind":"externalParam","text":"editType"},{"kind":"text","text":": "},{"kind":"typeIdentifier","identifier":"doc:\/\/Open-Jellycore\/documentation\/Open_Jellycore\/Jelly_EditReminderType","preciseIdentifier":"s:14Open_Jellycore22Jelly_EditReminderTypeO","text":"Jelly_EditReminderType"},{"kind":"text","text":"? = nil, "},{"kind":"externalParam","text":"title"},{"kind":"text","text":": "},{"kind":"typeIdentifier","identifier":"doc:\/\/Open-Jellycore\/documentation\/Open_Jellycore\/JellyString","preciseIdentifier":"s:14Open_Jellycore11JellyStringV","text":"JellyString"},{"kind":"text","text":"? = nil, "},{"kind":"externalParam","text":"note"},{"kind":"text","text":": "},{"kind":"typeIdentifier","identifier":"doc:\/\/Open-Jellycore\/documentation\/Open_Jellycore\/JellyString","preciseIdentifier":"s:14Open_Jellycore11JellyStringV","text":"JellyString"},{"kind":"text","text":"? = nil, "},{"kind":"externalParam","text":"dueDate"},{"kind":"text","text":": "},{"kind":"typeIdentifier","identifier":"doc:\/\/Open-Jellycore\/documentation\/Open_Jellycore\/JellyDate","preciseIdentifier":"s:14Open_Jellycore9JellyDateV","text":"JellyDate"},{"kind":"text","text":"? = nil, "},{"kind":"externalParam","text":"priority"},{"kind":"text","text":": "},{"kind":"typeIdentifier","identifier":"doc:\/\/Open-Jellycore\/documentation\/Open_Jellycore\/Jelly_ReminderPriority","preciseIdentifier":"s:14Open_Jellycore22Jelly_ReminderPriorityO","text":"Jelly_ReminderPriority"},{"kind":"text","text":"? = nil, "},{"kind":"externalParam","text":"list"},{"kind":"text","text":": "},{"kind":"typeIdentifier","identifier":"doc:\/\/Open-Jellycore\/documentation\/Open_Jellycore\/JellyString","preciseIdentifier":"s:14Open_Jellycore11JellyStringV","text":"JellyString"},{"kind":"text","text":"? = nil, "},{"kind":"externalParam","text":"location"},{"kind":"text","text":": "},{"kind":"typeIdentifier","identifier":"doc:\/\/Open-Jellycore\/documentation\/Open_Jellycore\/ShortcutsPlacemark","preciseIdentifier":"s:14Open_Jellycore18ShortcutsPlacemarkV","text":"ShortcutsPlacemark"},{"kind":"text","text":"? = nil, "},{"kind":"externalParam","text":"repeatType"},{"kind":"text","text":": "},{"kind":"typeIdentifier","identifier":"doc:\/\/Open-Jellycore\/documentation\/Open_Jellycore\/Jelly_RepeatType","preciseIdentifier":"s:14Open_Jellycore16Jelly_RepeatTypeO","text":"Jelly_RepeatType"},{"kind":"text","text":"? = nil, "},{"kind":"externalParam","text":"locationType"},{"kind":"text","text":": "},{"kind":"typeIdentifier","identifier":"doc:\/\/Open-Jellycore\/documentation\/Open_Jellycore\/Jelly_LocationAlertType","preciseIdentifier":"s:14Open_Jellycore23Jelly_LocationAlertTypeO","text":"Jelly_LocationAlertType"},{"kind":"text","text":"? = nil, "},{"kind":"externalParam","text":"alertDate"},{"kind":"text","text":": "},{"kind":"typeIdentifier","identifier":"doc:\/\/Open-Jellycore\/documentation\/Open_Jellycore\/JellyDate","preciseIdentifier":"s:14Open_Jellycore9JellyDateV","text":"JellyDate"},{"kind":"text","text":"? = nil, "},{"kind":"externalParam","text":"id"},{"kind":"text","text":": "},{"kind":"typeIdentifier","identifier":"doc:\/\/Open-Jellycore\/documentation\/Open_Jellycore\/JellyString","preciseIdentifier":"s:14Open_Jellycore11JellyStringV","text":"JellyString"},{"kind":"text","text":"? = nil)"}],"languages":["swift"],"platforms":["macOS"]}]}],"schemaVersion":{"major":0,"minor":3,"patch":0},"sections":[],"variants":[{"paths":["\/documentation\/open_jellycore\/editreminderparameter\/init(edittype:title:note:duedate:priority:list:location:repeattype:locationtype:alertdate:id:)"],"traits":[{"interfaceLanguage":"swift"}]}],"identifier":{"url":"doc:\/\/Open-Jellycore\/documentation\/Open_Jellycore\/EditReminderParameter\/init(editType:title:note:dueDate:priority:list:location:repeatType:locationType:alertDate:id:)","interfaceLanguage":"swift"},"kind":"symbol","metadata":{"fragments":[{"kind":"identifier","text":"init"},{"kind":"text","text":"("},{"kind":"externalParam","text":"editType"},{"kind":"text","text":": "},{"kind":"typeIdentifier","text":"Jelly_EditReminderType","preciseIdentifier":"s:14Open_Jellycore22Jelly_EditReminderTypeO"},{"kind":"text","text":"?, "},{"kind":"externalParam","text":"title"},{"kind":"text","text":": "},{"kind":"typeIdentifier","text":"JellyString","preciseIdentifier":"s:14Open_Jellycore11JellyStringV"},{"kind":"text","text":"?, "},{"kind":"externalParam","text":"note"},{"kind":"text","text":": "},{"kind":"typeIdentifier","text":"JellyString","preciseIdentifier":"s:14Open_Jellycore11JellyStringV"},{"kind":"text","text":"?, "},{"kind":"externalParam","text":"dueDate"},{"kind":"text","text":": "},{"kind":"typeIdentifier","text":"JellyDate","preciseIdentifier":"s:14Open_Jellycore9JellyDateV"},{"kind":"text","text":"?, "},{"kind":"externalParam","text":"priority"},{"kind":"text","text":": "},{"kind":"typeIdentifier","text":"Jelly_ReminderPriority","preciseIdentifier":"s:14Open_Jellycore22Jelly_ReminderPriorityO"},{"kind":"text","text":"?, "},{"kind":"externalParam","text":"list"},{"kind":"text","text":": "},{"kind":"typeIdentifier","text":"JellyString","preciseIdentifier":"s:14Open_Jellycore11JellyStringV"},{"kind":"text","text":"?, "},{"kind":"externalParam","text":"location"},{"kind":"text","text":": "},{"kind":"typeIdentifier","text":"ShortcutsPlacemark","preciseIdentifier":"s:14Open_Jellycore18ShortcutsPlacemarkV"},{"kind":"text","text":"?, "},{"kind":"externalParam","text":"repeatType"},{"kind":"text","text":": "},{"kind":"typeIdentifier","text":"Jelly_RepeatType","preciseIdentifier":"s:14Open_Jellycore16Jelly_RepeatTypeO"},{"kind":"text","text":"?, "},{"kind":"externalParam","text":"locationType"},{"kind":"text","text":": "},{"kind":"typeIdentifier","text":"Jelly_LocationAlertType","preciseIdentifier":"s:14Open_Jellycore23Jelly_LocationAlertTypeO"},{"kind":"text","text":"?, "},{"kind":"externalParam","text":"alertDate"},{"kind":"text","text":": "},{"kind":"typeIdentifier","text":"JellyDate","preciseIdentifier":"s:14Open_Jellycore9JellyDateV"},{"kind":"text","text":"?, "},{"kind":"externalParam","text":"id"},{"kind":"text","text":": "},{"kind":"typeIdentifier","text":"JellyString","preciseIdentifier":"s:14Open_Jellycore11JellyStringV"},{"kind":"text","text":"?)"}],"title":"init(editType:title:note:dueDate:priority:list:location:repeatType:locationType:alertDate:id:)","roleHeading":"Initializer","role":"symbol","symbolKind":"init","externalID":"s:14Open_Jellycore21EditReminderParameterV8editType5title4note7dueDate8priority4list8location06repeatG00nG005alertK02idAcA06Jelly_cdG0OSg_AA0R6StringVSgAtA0rK0VSgAA0r1_D8PriorityOSgAtA18ShortcutsPlacemarkVSgAA0r7_RepeatG0OSgAA0r14_LocationAlertG0OSgAwTtcfc","modules":[{"name":"Open-Jellycore"}]},"hierarchy":{"paths":[["doc:\/\/Open-Jellycore\/documentation\/Open_Jellycore","doc:\/\/Open-Jellycore\/documentation\/Open_Jellycore\/EditReminderParameter"]]},"references":{"doc://Open-Jellycore/documentation/Open_Jellycore":{"role":"collection","title":"Open-Jellycore","abstract":[],"identifier":"doc:\/\/Open-Jellycore\/documentation\/Open_Jellycore","kind":"symbol","type":"topic","url":"\/documentation\/open_jellycore"},"doc://Open-Jellycore/documentation/Open_Jellycore/EditReminderParameter/init(editType:title:note:dueDate:priority:list:location:repeatType:locationType:alertDate:id:)":{"role":"symbol","title":"init(editType:title:note:dueDate:priority:list:location:repeatType:locationType:alertDate:id:)","fragments":[{"kind":"identifier","text":"init"},{"kind":"text","text":"("},{"kind":"externalParam","text":"editType"},{"kind":"text","text":": "},{"kind":"typeIdentifier","text":"Jelly_EditReminderType","preciseIdentifier":"s:14Open_Jellycore22Jelly_EditReminderTypeO"},{"kind":"text","text":"?, "},{"kind":"externalParam","text":"title"},{"kind":"text","text":": "},{"kind":"typeIdentifier","text":"JellyString","preciseIdentifier":"s:14Open_Jellycore11JellyStringV"},{"kind":"text","text":"?, "},{"kind":"externalParam","text":"note"},{"kind":"text","text":": "},{"kind":"typeIdentifier","text":"JellyString","preciseIdentifier":"s:14Open_Jellycore11JellyStringV"},{"kind":"text","text":"?, "},{"kind":"externalParam","text":"dueDate"},{"kind":"text","text":": "},{"kind":"typeIdentifier","text":"JellyDate","preciseIdentifier":"s:14Open_Jellycore9JellyDateV"},{"kind":"text","text":"?, "},{"kind":"externalParam","text":"priority"},{"kind":"text","text":": "},{"kind":"typeIdentifier","text":"Jelly_ReminderPriority","preciseIdentifier":"s:14Open_Jellycore22Jelly_ReminderPriorityO"},{"kind":"text","text":"?, "},{"kind":"externalParam","text":"list"},{"kind":"text","text":": "},{"kind":"typeIdentifier","text":"JellyString","preciseIdentifier":"s:14Open_Jellycore11JellyStringV"},{"kind":"text","text":"?, "},{"kind":"externalParam","text":"location"},{"kind":"text","text":": "},{"kind":"typeIdentifier","text":"ShortcutsPlacemark","preciseIdentifier":"s:14Open_Jellycore18ShortcutsPlacemarkV"},{"kind":"text","text":"?, "},{"kind":"externalParam","text":"repeatType"},{"kind":"text","text":": "},{"kind":"typeIdentifier","text":"Jelly_RepeatType","preciseIdentifier":"s:14Open_Jellycore16Jelly_RepeatTypeO"},{"kind":"text","text":"?, "},{"kind":"externalParam","text":"locationType"},{"kind":"text","text":": "},{"kind":"typeIdentifier","text":"Jelly_LocationAlertType","preciseIdentifier":"s:14Open_Jellycore23Jelly_LocationAlertTypeO"},{"kind":"text","text":"?, "},{"kind":"externalParam","text":"alertDate"},{"kind":"text","text":": "},{"kind":"typeIdentifier","text":"JellyDate","preciseIdentifier":"s:14Open_Jellycore9JellyDateV"},{"kind":"text","text":"?, "},{"kind":"externalParam","text":"id"},{"kind":"text","text":": "},{"kind":"typeIdentifier","text":"JellyString","preciseIdentifier":"s:14Open_Jellycore11JellyStringV"},{"kind":"text","text":"?)"}],"abstract":[],"identifier":"doc:\/\/Open-Jellycore\/documentation\/Open_Jellycore\/EditReminderParameter\/init(editType:title:note:dueDate:priority:list:location:repeatType:locationType:alertDate:id:)","kind":"symbol","type":"topic","url":"\/documentation\/open_jellycore\/editreminderparameter\/init(edittype:title:note:duedate:priority:list:location:repeattype:locationtype:alertdate:id:)"},"doc://Open-Jellycore/documentation/Open_Jellycore/EditReminderParameter":{"role":"symbol","title":"EditReminderParameter","fragments":[{"kind":"keyword","text":"struct"},{"kind":"text","text":" "},{"kind":"identifier","text":"EditReminderParameter"}],"abstract":[],"identifier":"doc:\/\/Open-Jellycore\/documentation\/Open_Jellycore\/EditReminderParameter","kind":"symbol","type":"topic","navigatorTitle":[{"kind":"identifier","text":"EditReminderParameter"}],"url":"\/documentation\/open_jellycore\/editreminderparameter"},"doc://Open-Jellycore/documentation/Open_Jellycore/Jelly_LocationAlertType":{"role":"symbol","title":"Jelly_LocationAlertType","fragments":[{"kind":"keyword","text":"enum"},{"kind":"text","text":" "},{"kind":"identifier","text":"Jelly_LocationAlertType"}],"abstract":[],"identifier":"doc:\/\/Open-Jellycore\/documentation\/Open_Jellycore\/Jelly_LocationAlertType","kind":"symbol","type":"topic","navigatorTitle":[{"kind":"identifier","text":"Jelly_LocationAlertType"}],"url":"\/documentation\/open_jellycore\/jelly_locationalerttype"},"doc://Open-Jellycore/documentation/Open_Jellycore/JellyString":{"role":"symbol","title":"JellyString","fragments":[{"kind":"keyword","text":"struct"},{"kind":"text","text":" "},{"kind":"identifier","text":"JellyString"}],"abstract":[{"type":"text","text":"A representation of a String that supports converting interpolated values into Shortcuts attachments."}],"identifier":"doc:\/\/Open-Jellycore\/documentation\/Open_Jellycore\/JellyString","kind":"symbol","type":"topic","navigatorTitle":[{"kind":"identifier","text":"JellyString"}],"url":"\/documentation\/open_jellycore\/jellystring"},"doc://Open-Jellycore/documentation/Open_Jellycore/ShortcutsPlacemark":{"role":"symbol","title":"ShortcutsPlacemark","fragments":[{"kind":"keyword","text":"struct"},{"kind":"text","text":" "},{"kind":"identifier","text":"ShortcutsPlacemark"}],"abstract":[],"identifier":"doc:\/\/Open-Jellycore\/documentation\/Open_Jellycore\/ShortcutsPlacemark","kind":"symbol","type":"topic","navigatorTitle":[{"kind":"identifier","text":"ShortcutsPlacemark"}],"url":"\/documentation\/open_jellycore\/shortcutsplacemark"},"doc://Open-Jellycore/documentation/Open_Jellycore/JellyDate":{"role":"symbol","title":"JellyDate","fragments":[{"kind":"keyword","text":"struct"},{"kind":"text","text":" "},{"kind":"identifier","text":"JellyDate"}],"abstract":[{"type":"text","text":"This type represents a date. It can take date input in almost any date format and convert it into a Swift Date value. This value is then encoded to the proper date values that shortcuts uses."}],"identifier":"doc:\/\/Open-Jellycore\/documentation\/Open_Jellycore\/JellyDate","kind":"symbol","type":"topic","navigatorTitle":[{"kind":"identifier","text":"JellyDate"}],"url":"\/documentation\/open_jellycore\/jellydate"},"doc://Open-Jellycore/documentation/Open_Jellycore/Jelly_ReminderPriority":{"role":"symbol","title":"Jelly_ReminderPriority","fragments":[{"kind":"keyword","text":"enum"},{"kind":"text","text":" "},{"kind":"identifier","text":"Jelly_ReminderPriority"}],"abstract":[],"identifier":"doc:\/\/Open-Jellycore\/documentation\/Open_Jellycore\/Jelly_ReminderPriority","kind":"symbol","type":"topic","navigatorTitle":[{"kind":"identifier","text":"Jelly_ReminderPriority"}],"url":"\/documentation\/open_jellycore\/jelly_reminderpriority"},"doc://Open-Jellycore/documentation/Open_Jellycore/Jelly_EditReminderType":{"role":"symbol","title":"Jelly_EditReminderType","fragments":[{"kind":"keyword","text":"enum"},{"kind":"text","text":" "},{"kind":"identifier","text":"Jelly_EditReminderType"}],"abstract":[],"identifier":"doc:\/\/Open-Jellycore\/documentation\/Open_Jellycore\/Jelly_EditReminderType","kind":"symbol","type":"topic","navigatorTitle":[{"kind":"identifier","text":"Jelly_EditReminderType"}],"url":"\/documentation\/open_jellycore\/jelly_editremindertype"},"doc://Open-Jellycore/documentation/Open_Jellycore/Jelly_RepeatType":{"role":"symbol","title":"Jelly_RepeatType","fragments":[{"kind":"keyword","text":"enum"},{"kind":"text","text":" "},{"kind":"identifier","text":"Jelly_RepeatType"}],"abstract":[],"identifier":"doc:\/\/Open-Jellycore\/documentation\/Open_Jellycore\/Jelly_RepeatType","kind":"symbol","type":"topic","navigatorTitle":[{"kind":"identifier","text":"Jelly_RepeatType"}],"url":"\/documentation\/open_jellycore\/jelly_repeattype"}}}